.gitignore
.readthedocs.yaml
.travis.yml
COPYING
ChangeLog
MANIFEST.in
README.rst
codemeta.json
requirements.txt
setup.cfg
setup.py
.github/workflows/clam.yml
CLAM.egg-info/PKG-INFO
CLAM.egg-info/SOURCES.txt
CLAM.egg-info/dependency_links.txt
CLAM.egg-info/entry_points.txt
CLAM.egg-info/requires.txt
CLAM.egg-info/top_level.txt
clam/__init__.py
clam/clamclient.py
clam/clamdispatcher.py
clam/clamnewproject.py
clam/clamrunjob.py
clam/clamservice.py
clam/clients/clienttest.py
clam/clients/textstats.py
clam/common/__init__.py
clam/common/auth.py
clam/common/client.py
clam/common/converters.py
clam/common/data.py
clam/common/digestauth.py
clam/common/formats.py
clam/common/languages.py
clam/common/oauth.py
clam/common/parameters.py
clam/common/status.py
clam/common/util.py
clam/common/viewers.py
clam/config/__init__.py
clam/config/actiontest.py
clam/config/authactiontest.py
clam/config/authtest.py
clam/config/constrainttest.py
clam/config/defaults.py
clam/config/example.wsgi
clam/config/forwardauthtest.py
clam/config/freqlist.py
clam/config/multiplier.py
clam/config/nginx-clamservices-conf
clam/config/oauthtest.py
clam/config/setup_template.py
clam/config/template.Dockerfile
clam/config/template.config.yml
clam/config/template.py
clam/config/test.py
clam/config/test2.py
clam/config/textstats.py
clam/config/textstats1.py
clam/config/textstats2.py
clam/config/textstats3.py
clam/static/ajaxupload.js
clam/static/back.png
clam/static/base.css
clam/static/bootstrap.min.css
clam/static/bootstrap.min.js
clam/static/clam.js
clam/static/delete.png
clam/static/fine-uploader.min.css
clam/static/fineuploader.css
clam/static/info.xsl
clam/static/interface.xsl
clam/static/jquery-3.7.1.min.js
clam/static/jquery.dataTables.min.css
clam/static/jquery.dataTables.min.js
clam/static/jquery.fine-uploader.js
clam/static/jquery.fine-uploader.min.js
clam/static/jquery.fineuploader-3.1.js
clam/static/jquery.fineuploader-3.1.min.js
clam/static/loading.gif
clam/static/login.xsl
clam/static/open-iconic-bootstrap.min.css
clam/static/open-iconic.eot
clam/static/open-iconic.otf
clam/static/open-iconic.svg
clam/static/open-iconic.ttf
clam/static/open-iconic.woff
