Metadata-Version: 2.4
Name: CLAM
Version: 3.2.14
Summary: Turns command-line tools into fully-fledged RESTful webservices with an auto-generated web-interface for human end-users.
Home-page: https://proycon.github.io/clam
Author: Maarten van Gompel
Author-email: proycon@anaproy.nl
License: GPL-3.0-only
Keywords: SaaS,webservice,rest
Classifier: Development Status :: 5 - Production/Stable
Classifier: Topic :: Internet :: WWW/HTTP :: WSGI :: Application
Classifier: Topic :: Text Processing :: Linguistic
Classifier: Programming Language :: Python :: 3.6
Classifier: Programming Language :: Python :: 3.7
Classifier: Programming Language :: Python :: 3.8
Classifier: Programming Language :: Python :: 3.9
Classifier: Programming Language :: Python :: 3.10
Classifier: Programming Language :: Python :: 3.11
Classifier: Programming Language :: Python :: 3.12
Classifier: Operating System :: POSIX
Classifier: Intended Audience :: Developers
Classifier: Intended Audience :: Science/Research
Classifier: License :: OSI Approved :: GNU General Public License v3 (GPLv3)
License-File: COPYING
Requires-Dist: flask>=2.0.1
Requires-Dist: lxml>=4.6.0
Requires-Dist: requests
Requires-Dist: requests_oauthlib
Requires-Dist: requests_toolbelt
Requires-Dist: certifi
Requires-Dist: pyyaml
Dynamic: author
Dynamic: author-email
Dynamic: classifier
Dynamic: description
Dynamic: home-page
Dynamic: keywords
Dynamic: license
Dynamic: license-file
Dynamic: requires-dist
Dynamic: summary
